{
  "title": "GUIDA PER ALLEVATORI AVICOLI CON RACCOMANDAZIONI SU COME IMPLEMENTARE CORRETTAMENTE LA NORMATIVA SULLA BIOSICUREZZA NEI LORO ALLEVAMENTI",
  "subtitle": "",
  "description": "A practical guide to help poultry farmers implement biosafety regulations effectively. It covers essential biosecurity elements, monitoring activities, prudent antibiotic use, and examples of best practices.",
  "locations": [
    "Hungary",
    "European Union"
  ],
  "topic": "livestock",
  "theme": "Poultry biosafety regulations",
  "keywords": [
    "poultry farming",
    "biosafety",
    "biosecurity",
    "regulations",
    "avian influenza",
    "disease prevention",
    "prudent antibiotic use",
    "monitoring"
  ],
  "size": {
    "pages": 2,
    "bytes": 623526
  },
  "valid_structure": true
}