{
  "title": "AUDITS BIOSECURITE (PAR LES PROFESSIONNELS) FOCUS SUR LES INTEGRATIONS",
  "subtitle": "",
  "description": "This document examines biosecurity audits conducted by integrated poultry companies in Italy, outlining the organization of vertically integrated production chains and the roles of company veterinarians and technicians. It details the evaluation processes, policies, and corrective actions used during professional audits to ensure compliance in poultry farming operations.",
  "locations": [
    "Italy"
  ],
  "topic": "livestock",
  "theme": "Integrated poultry biosecurity",
  "keywords": [
    "Poultry",
    "Biosecurity audits",
    "Vertical integration",
    "Integrated companies",
    "Veterinarians",
    "Technicians",
    "Production chain",
    "Corrective actions",
    "Livestock management"
  ],
  "size": {
    "pages": 3,
    "bytes": 331181
  },
  "valid_structure": true
}