{
  "title": "A BIO-INSPIRED MULTI-LAYER FILTER SYSTEM USING BIOCHAR ADSORBENTS FOR WATER AND NUTRIENT UPTAKE",
  "subtitle": "",
  "description": "A factsheet presenting a prototype multi-layer vertical filter system using biochar adsorbents to retain and recover water and nutrients from agricultural runoff. It details the design, setup, technical requirements, monitoring methods, and potential benefits of the system tested in Mistelbach, Austria.",
  "locations": [
    "Austria"
  ],
  "topic": "environment",
  "theme": "Multi-layer biochar filter",
  "keywords": [
    "biochar",
    "multi-layer filter",
    "agricultural runoff",
    "water retention",
    "nutrient recovery",
    "vertical-flow system",
    "drainage system",
    "experimental prototype"
  ],
  "size": {
    "pages": 7,
    "bytes": 621698
  },
  "valid_structure": true
}