{
  "title": "Living mulches: management in conventional wheat farming",
  "subtitle": "",
  "description": "This practice abstract provides guidelines for managing living mulches in conventional wheat farming to maximize nitrogen supply and crop performance while minimizing competition. It outlines recommended sowing times, biomass thresholds, and strategies for regulating or destroying cover crops throughout the growing season.",
  "locations": [
    "Europe",
    "Provence (South France)"
  ],
  "topic": "crop farming",
  "theme": "Living mulch management",
  "keywords": [
    "living mulch",
    "cover crops",
    "wheat farming",
    "competition management",
    "nitrogen supply",
    "soil tillage",
    "herbicide application",
    "crop establishment"
  ],
  "size": {
    "pages": 2,
    "bytes": 344546
  },
  "valid_structure": true
}