{
  "title": "AGRICULTURAL KNOWLEDGE: LINKING FARMERS, ADVISORS AND RESEARCHERS TO BOOST INNOVATION",
  "subtitle": "",
  "description": "A practice abstract examining how the evolving advisory services landscape in Flanders influences farmers' decision-making and innovation uptake. It summarises findings from the H2020 AgriLink project, highlighting the roles of farmer organisations, private advisors, and peer networks in farm advisory systems.",
  "locations": [
    "Belgium",
    "Flanders"
  ],
  "topic": "society",
  "theme": "Farm advisory landscape",
  "keywords": [
    "farm advisory services",
    "farmers' organisations",
    "agricultural knowledge",
    "AKIS",
    "peer-to-peer learning",
    "innovation uptake",
    "decision-making",
    "farmer networks",
    "private advisors"
  ],
  "size": {
    "pages": 2,
    "bytes": 354584
  },
  "valid_structure": true
}